README.rst
setup.py
Greyskull.egg-info/PKG-INFO
Greyskull.egg-info/SOURCES.txt
Greyskull.egg-info/dependency_links.txt
Greyskull.egg-info/requires.txt
Greyskull.egg-info/top_level.txt
greyskull/__init__.py
greyskull/bencode.py
greyskull/ip_utils.py
greyskull/storage.py
greyskull/urls.py