Metadata-Version: 1.1
Name: Greyskull
Version: 0.0.1.dev1
Summary: A lightweight, bittorrent-compatible, NTrack tracker
Home-page: http://github.com/xj9/greyskull
Author: Carlos Killpack
Author-email: carlos.killpack@rocketmail.com
License: MIT/ISC
Platform: UNKNOWN
Classifier: License :: Public Domain
Classifier: License :: OSI Approved
Classifier: License :: OSI Approved :: ISC License (ISCL)
Classifier: License :: OSI Approved :: MIT License
Classifier: Operating System :: POSIX
Classifier: Programming Language :: Python :: 3
Classifier: Topic :: Internet
Classifier: Topic :: Internet :: WWW/HTTP
Classifier: Topic :: System :: Networking
